CHANGES.rst
MANIFEST.in
README.rst
setup.py
docs/LICENSE.GPL
docs/LICENSE.txt
pd/__init__.py
pd.plonedemografico.egg-info/PKG-INFO
pd.plonedemografico.egg-info/SOURCES.txt
pd.plonedemografico.egg-info/dependency_links.txt
pd.plonedemografico.egg-info/entry_points.txt
pd.plonedemografico.egg-info/namespace_packages.txt
pd.plonedemografico.egg-info/not-zip-safe
pd.plonedemografico.egg-info/requires.txt
pd.plonedemografico.egg-info/top_level.txt
pd/plonedemografico/README.rst
pd/plonedemografico/__init__.py
pd/plonedemografico/config.py
pd/plonedemografico/configure.zcml
pd/plonedemografico/i18n.sh
pd/plonedemografico/testing.py
pd/plonedemografico/EXTENSIONS/install.py
pd/plonedemografico/browser/__init__.py
pd/plonedemografico/browser/configure.zcml
pd/plonedemografico/browser/interfaces.py
pd/plonedemografico/browser/prenotazione_add_ro.pt
pd/plonedemografico/browser/prenotazione_add_ro.py
pd/plonedemografico/browser/slots.py
pd/plonedemografico/browser/tipologie.py
pd/plonedemografico/locales/pd.plonedemografico.pot
pd/plonedemografico/locales/en/LC_MESSAGES/pd.plonedemografico.po
pd/plonedemografico/locales/it/LC_MESSAGES/pd.plonedemografico.po
pd/plonedemografico/profiles/default/browserlayer.xml
pd/plonedemografico/profiles/default/metadata.xml
pd/plonedemografico/profiles/uninstall/browserlayer.xml
pd/plonedemografico/tests/__init__.py
pd/plonedemografico/tests/base.py
pd/plonedemografico/tests/robot_test.txt
pd/plonedemografico/tests/test_doctest.py
pd/plonedemografico/tests/test_example.py
pd/plonedemografico/tests/test_robot.py