Metadata-Version: 1.1
Name: pd.plonedemografico
Version: 1.0.1
Summary: PD Prenotazioni for Plone Demografico
Home-page: http://svn.plone.org/svn/collective/
Author: RedTurtle Technology
Author-email: sviluppoplone@redturtle.it
License: gpl
Platform: UNKNOWN
Classifier: Framework :: Plone
Classifier: Intended Audience :: Developers
